dcrx/__init__.py
dcrx/directive.py
dcrx/image.py
dcrx/cli/__init__.py
dcrx/cli/compile.py
dcrx/cli/new.py
dcrx/cli/root.py
dcrx/cli/validate.py
dcrx/cli/templates/__init__.py
dcrx/cli/templates/basic.py
dcrx/layers/__init__.py
dcrx/layers/add.py
dcrx/layers/arg.py
dcrx/layers/cmd.py
dcrx/layers/copy.py
dcrx/layers/entrypoint.py
dcrx/layers/env.py
dcrx/layers/expose.py
dcrx/layers/healthcheck.py
dcrx/layers/label.py
dcrx/layers/maintainer.py
dcrx/layers/onbuild.py
dcrx/layers/run.py
dcrx/layers/shell.py
dcrx/layers/stage.py
dcrx/layers/stopsignal.py
dcrx/layers/user.py
dcrx/layers/volume.py
dcrx/layers/workdir.py
dcrx/layers/mount_types/__init__.py
dcrx/layers/mount_types/bind_mount.py
dcrx/layers/mount_types/cache_mount.py
dcrx/layers/mount_types/secret_mount.py
dcrx/layers/mount_types/ssh_mount.py
dcrx/layers/mount_types/tmpfs_mount.py
dcrx/memory_file/__init__.py
dcrx/memory_file/memory_file.py
dcrx/queries/__init__.py
dcrx/queries/layer_query.py
dcrx-0.5.1.dist-info/licenses/LICENSE
dcrx-0.5.1.dist-info/METADATA
dcrx-0.5.1.dist-info/WHEEL
dcrx-0.5.1.dist-info/entry_points.txt
dcrx-0.5.1.dist-info/top_level.txt
dcrx-0.5.1.dist-info/RECORD
