Metadata-Version: 2.4
Name: dcrx
Version: 0.5.1
Summary: A library for typesafe, programmatic generation of Docker images via SQL-builder like API.
Author-email: Ada Lundhe <adalundhe@lundhe.audio>
License: MIT License
Keywords: pypi,cicd,python,setup,docker,infra,devops
Classifier: Programming Language :: Python :: 3.11
Classifier: Programming Language :: Python :: 3.12
Classifier: Programming Language :: Python :: 3.13
Classifier: License :: OSI Approved :: MIT License
Classifier: Operating System :: OS Independent
Requires-Python: >=3.11
License-File: LICENSE
Requires-Dist: pydantic
Requires-Dist: hyperlight-cocoa
Requires-Dist: taskex
Dynamic: license-file
